refrapy/__init__.py
refrapy/__main__.py
refrapy/refrainv.py
refrapy/refrapick.py
refrapy/data/field_example_01/data/2001.dat
refrapy/data/field_example_01/data/2002.dat
refrapy/data/field_example_01/data/2003.dat
refrapy/data/field_example_01/data/2004.dat
refrapy/data/field_example_01/data/2005.dat
refrapy/data/field_example_01/picks/field_example_01.sgt
refrapy/data/field_example_02/data/1.dat
refrapy/data/field_example_02/data/10.dat
refrapy/data/field_example_02/data/3.dat
refrapy/data/field_example_02/data/4.dat
refrapy/data/field_example_02/data/5.dat
refrapy/data/field_example_02/data/6.dat
refrapy/data/field_example_02/data/7.dat
refrapy/data/field_example_02/data/8.dat
refrapy/data/field_example_02/data/9.dat
refrapy/data/field_example_02/gps/field_example_02_coordinates.txt
refrapy/data/field_example_02/gps/field_example_02_topography.txt
refrapy/data/field_example_02/picks/field_example_02.sgt
refrapy/images/abrir.gif
refrapy/images/baixo.gif
refrapy/images/camadas.gif
refrapy/images/cima.gif
refrapy/images/clip.gif
refrapy/images/cortar.gif
refrapy/images/fechar.gif
refrapy/images/fill_neg.gif
refrapy/images/fill_null.gif
refrapy/images/fill_pos.gif
refrapy/images/grafico.gif
refrapy/images/ico_3d.gif
refrapy/images/ico_allPicks.gif
refrapy/images/ico_filter.gif
refrapy/images/ico_fit.gif
refrapy/images/ico_help.gif
refrapy/images/ico_loadPicks.gif
refrapy/images/ico_loadProject.gif
refrapy/images/ico_mergeResults.gif
refrapy/images/ico_newProject.gif
refrapy/images/ico_plotOptions.gif
refrapy/images/ico_refrapy.gif
refrapy/images/ico_refrapy.ico
refrapy/images/ico_refrapy.png
refrapy/images/ico_resample.gif
refrapy/images/ico_restoreTraces.gif
refrapy/images/ico_shotTime.gif
refrapy/images/ico_survey.gif
refrapy/images/ico_velmesh.gif
refrapy/images/invert.gif
refrapy/images/layer1.gif
refrapy/images/layer2.gif
refrapy/images/layer3.gif
refrapy/images/ligar.gif
refrapy/images/limpar.gif
refrapy/images/mais.gif
refrapy/images/menos.gif
refrapy-0.2.4.1.dist-info/METADATA
refrapy-0.2.4.1.dist-info/WHEEL
refrapy-0.2.4.1.dist-info/entry_points.txt
refrapy-0.2.4.1.dist-info/licenses/LICENSE
refrapy-0.2.4.1.dist-info/RECORD
