Metadata-Version: 2.4
Name: refrapy
Version: 0.2.4.1
Summary: Refrapy is a Python software package with a graphical interface for seismic refraction data analysis.
Project-URL: Source, https://github.com/AlgoSismos/Refrapy
Author-email: Victor Guedes <vjs279@hotmail.com>, Susanne Maciel <susanne@unb.br>
Maintainer-email: Marco Aurélio Barbosa <aureliobarbosa@gmail.com>
License: Copyright (C) 2021 Victor Guedes
License-File: LICENSE
Keywords: geophysics,seismic refraction
Classifier: Development Status :: 4 - Beta
Classifier: Intended Audience :: Science/Research
Classifier: License :: OSI Approved :: MIT License
Classifier: Programming Language :: Python
Classifier: Programming Language :: Python :: Implementation :: CPython
Requires-Python: <3.13,>=3.10
Requires-Dist: numpy>=1.19
Requires-Dist: obspy>=1.3
Requires-Dist: pmw>=2.0
Requires-Dist: pygimli>=1.5
Requires-Dist: scipy>=1.8.0
